markdown_latex_prerender/__init__.py
markdown_latex_prerender/extension.py
markdown_latex_prerender/render.py
markdown_latex_prerender-0.1.0.dist-info/METADATA
markdown_latex_prerender-0.1.0.dist-info/WHEEL
markdown_latex_prerender-0.1.0.dist-info/RECORD
