Metadata-Version: 2.1
Name: markdown-latex-prerender
Version: 0.1.0
Summary: An extension to python-markdown that replaces inline latex with prerendered SVGs
License: MIT
Author: Anton Lydike
Author-email: me@antonlydike.de
Requires-Python: >=3.10,<4.0
Classifier: License :: OSI Approved :: MIT License
Classifier: Programming Language :: Python :: 3
Classifier: Programming Language :: Python :: 3.10
Classifier: Programming Language :: Python :: 3.11
Classifier: Programming Language :: Python :: 3.12
Classifier: Programming Language :: Python :: 3.13
Requires-Dist: markdown (>=3.7,<4.0)
